mcp_orchestrator/.gitkeep
mcp_orchestrator/__init__.py
mcp_orchestrator/cli.py
mcp_orchestrator/cli_init.py
mcp_orchestrator/telemetry.py
mcp_orchestrator/crypto/__init__.py
mcp_orchestrator/crypto/signing.py
mcp_orchestrator/diff/__init__.py
mcp_orchestrator/diff/config_diff.py
mcp_orchestrator/mcp/__init__.py
mcp_orchestrator/mcp/server.py
mcp_orchestrator/registry/__init__.py
mcp_orchestrator/registry/clients.py
mcp_orchestrator/storage/__init__.py
mcp_orchestrator/storage/artifacts.py
mcp_orchestration-0.1.0.dist-info/METADATA
mcp_orchestration-0.1.0.dist-info/WHEEL
mcp_orchestration-0.1.0.dist-info/entry_points.txt
mcp_orchestration-0.1.0.dist-info/licenses/LICENSE
mcp_orchestration-0.1.0.dist-info/RECORD
