Metadata-Version: 2.4
Name: mcp-orchestration
Version: 0.1.0
Summary: MCP server for centralized configuration management with cryptographic signatures and content-addressable storage
Project-URL: Homepage, https://github.com/liminalcommons/mcp-orchestration
Project-URL: Repository, https://github.com/liminalcommons/mcp-orchestration
Project-URL: Issues, https://github.com/liminalcommons/mcp-orchestration/issues
Project-URL: Documentation, https://github.com/liminalcommons/mcp-orchestration#readme
Author-email: Victor Piper <victor@liminalcommons.org>
License: MIT
License-File: LICENSE
Keywords: configuration,cryptography,mcp,model-context-protocol,orchestration
Classifier: Development Status :: 4 - Beta
Classifier: Intended Audience :: Developers
Classifier: License :: OSI Approved :: MIT License
Classifier: Programming Language :: Python :: 3
Classifier: Programming Language :: Python :: 3.12
Classifier: Topic :: Software Development :: Libraries :: Python Modules
Classifier: Topic :: System :: Systems Administration
Requires-Python: >=3.12
Requires-Dist: chora-compose>=0.1.0
Requires-Dist: click>=8.0.0
Requires-Dist: cryptography>=41.0.0
Requires-Dist: fastmcp>=0.3.0
Requires-Dist: pydantic-settings>=2.0.0
Requires-Dist: pydantic>=2.0.0
Requires-Dist: python-dotenv>=1.0.0
Provides-Extra: dev
Requires-Dist: black==24.10.0; extra == 'dev'
Requires-Dist: mypy==1.11.0; extra == 'dev'
Requires-Dist: pre-commit==4.0.1; extra == 'dev'
Requires-Dist: pytest-asyncio==0.24.0; extra == 'dev'
Requires-Dist: pytest-cov==6.0.0; extra == 'dev'
Requires-Dist: pytest==8.3.0; extra == 'dev'
Requires-Dist: ruff==0.7.0; extra == 'dev'
Provides-Extra: release
Requires-Dist: build==1.0.3; extra == 'release'
Requires-Dist: twine==4.0.2; extra == 'release'
